{"cameraMode":{"drawMode":0,"name":"Shaded","section":"Shading Mode"},"sceneLighting":true,"audioPlay":false,"sceneViewState":{"m_AlwaysRefresh":false,"showFog":true,"showSkybox":true,"showFlares":true,"showImageEffects":true,"showParticleSystems":true,"showVisualEffectGraphs":true,"m_FxEnabled":true},"in2DMode":false,"pivot":{"x":5.365311622619629,"y":0.25734761357307436,"z":27.398338317871095},"rotation":{"x":0.07289425283670426,"y":0.3765372931957245,"z":-0.029744325205683709,"w":0.923079252243042},"size":10.0,"orthographic":false}